MANIFEST.in
README.md
flask_crossdomain.py
setup.py
flask_crossdomain.egg-info/PKG-INFO
flask_crossdomain.egg-info/SOURCES.txt
flask_crossdomain.egg-info/dependency_links.txt
flask_crossdomain.egg-info/requires.txt
flask_crossdomain.egg-info/top_level.txt