Metadata-Version: 1.0
Name: flask-crossdomain
Version: 0.1
Summary: HTTP Access Control helper.
Home-page: http://github.com/iurisilvio/flask-crossdomain
Author: Iuri de Silvio
Author-email: iurisilvio@gmail.com
License: Public Domain
Platform: UNKNOWN
Classifier: Development Status :: 5 - Production/Stable
Classifier: Intended Audience :: Developers
Classifier: License :: Public Domain
Classifier: Natural Language :: English
Classifier: Operating System :: OS Independent
Classifier: Programming Language :: Python :: 2
Classifier: Programming Language :: Python :: 3
Classifier: Topic :: Software Development :: Libraries :: Python Modules
